django_s3_storage/__init__.py
django_s3_storage/storage.py
django_s3_storage/management/__init__.py
django_s3_storage/management/commands/__init__.py
django_s3_storage/management/commands/s3_sync_meta.py
django_s3_storage-0.15.0.dist-info/LICENSE
django_s3_storage-0.15.0.dist-info/METADATA
django_s3_storage-0.15.0.dist-info/WHEEL
django_s3_storage-0.15.0.dist-info/top_level.txt
django_s3_storage-0.15.0.dist-info/RECORD
