Metadata-Version: 2.1
Name: django-s3-storage
Version: 0.15.0
Summary: Django Amazon S3 file storage.
Home-page: https://github.com/etianen/django-s3-storage
Author: Dave Hall
Author-email: dave@etianen.com
License: BSD
Classifier: Development Status :: 4 - Beta
Classifier: Environment :: Web Environment
Classifier: Intended Audience :: Developers
Classifier: License :: OSI Approved :: BSD License
Classifier: Operating System :: OS Independent
Classifier: Programming Language :: Python
Classifier: Programming Language :: Python :: 3.7
Classifier: Programming Language :: Python :: 3.8
Classifier: Programming Language :: Python :: 3.9
Classifier: Programming Language :: Python :: 3.10
Classifier: Framework :: Django
Classifier: Framework :: Django :: 3.2
Classifier: Framework :: Django :: 4.0
Classifier: Framework :: Django :: 4.1
License-File: LICENSE
Requires-Dist: django>=3.2
Requires-Dist: boto3<2,>=1.4.4
